mlc_llm.py
mlc_llm_nightly-99.99.105.dist-info/METADATA
mlc_llm_nightly-99.99.105.dist-info/WHEEL
mlc_llm_nightly-99.99.105.dist-info/top_level.txt
mlc_llm_nightly-99.99.105.dist-info/RECORD
