Metadata-Version: 2.1
Name: mlc-llm-nightly
Version: 99.99.105
Summary: PoC. Contact RedYetiHacks@wearehackerone.com for information.
